package com.bumptech.glide.load.engine;

import android.util.Log;
import com.bumptech.glide.Priority;
import com.bumptech.glide.Registry;
import com.bumptech.glide.Registry.NoResultEncoderAvailableException;
import com.bumptech.glide.load.DataSource;
import com.bumptech.glide.load.EncodeStrategy;
import g3.a.f;
import java.util.ArrayList;
import java.util.List;
import java.util.Map;
import n2.g;
import p2.a;

class DecodeJob<R>
  implements e.a, Runnable, Comparable<DecodeJob<?>>, a.f
{
  private n2.b D;
  private n2.b E;
  private Object F;
  private DataSource G;
  private com.bumptech.glide.load.data.d<?> H;
  private volatile e I;
  private volatile boolean J;
  private volatile boolean K;
  private boolean L;
  private final f<R> a = new f();
  private final List<Throwable> b = new ArrayList();
  private final g3.c c = g3.c.a();
  private final e d;
  private final androidx.core.util.e<DecodeJob<?>> e;
  private final d<?> f = new d();
  private final f g = new f();
  private com.bumptech.glide.d h;
  private n2.b i;
  private Priority j;
  private l k;
  private int l;
  private int m;
  private h n;
  private n2.d o;
  private b<R> p;
  private int q;
  private Stage r;
  private RunReason v;
  private long w;
  private boolean x;
  private Object y;
  private Thread z;
  
  DecodeJob(e parame, androidx.core.util.e<DecodeJob<?>> parame1)
  {
    this.d = parame;
    this.e = parame1;
  }
  
  private void C()
  {
    this.g.e();
    this.f.a();
    this.a.a();
    this.J = false;
    this.h = null;
    this.i = null;
    this.o = null;
    this.j = null;
    this.k = null;
    this.p = null;
    this.r = null;
    this.I = null;
    this.z = null;
    this.D = null;
    this.F = null;
    this.G = null;
    this.H = null;
    this.w = 0L;
    this.K = false;
    this.y = null;
    this.b.clear();
    this.e.a(this);
  }
  
  private void D()
  {
    this.z = Thread.currentThread();
    this.w = f3.f.b();
    boolean bool1 = false;
    boolean bool2;
    do
    {
      bool2 = bool1;
      if (this.K) {
        break;
      }
      bool2 = bool1;
      if (this.I == null) {
        break;
      }
      bool1 = this.I.a();
      bool2 = bool1;
      if (bool1) {
        break;
      }
      this.r = p(this.r);
      this.I = o();
    } while (this.r != Stage.SOURCE);
    c();
    return;
    if (((this.r == Stage.FINISHED) || (this.K)) && (!bool2)) {
      x();
    }
  }
  
  private <Data, ResourceType> s<R> E(Data paramData, DataSource paramDataSource, q<Data, ResourceType, R> paramq)
    throws GlideException
  {
    n2.d locald = q(paramDataSource);
    paramData = this.h.i().l(paramData);
    try
    {
      int i1 = this.l;
      int i2 = this.m;
      c localc = new com/bumptech/glide/load/engine/DecodeJob$c;
      localc.<init>(this, paramDataSource);
      paramDataSource = paramq.a(paramData, locald, i1, i2, localc);
      return paramDataSource;
    }
    finally
    {
      paramData.b();
    }
  }
  
  private void F()
  {
    int i1 = a.a[this.v.ordinal()];
    if (i1 != 1)
    {
      if (i1 != 2)
      {
        if (i1 == 3)
        {
          n();
        }
        else
        {
          StringBuilder localStringBuilder = new StringBuilder();
          localStringBuilder.append("Unrecognized run reason: ");
          localStringBuilder.append(this.v);
          throw new IllegalStateException(localStringBuilder.toString());
        }
      }
      else {
        D();
      }
    }
    else
    {
      this.r = p(Stage.INITIALIZE);
      this.I = o();
      D();
    }
  }
  
  private void G()
  {
    this.c.c();
    if (this.J)
    {
      Object localObject;
      if (this.b.isEmpty())
      {
        localObject = null;
      }
      else
      {
        localObject = this.b;
        localObject = (Throwable)((List)localObject).get(((List)localObject).size() - 1);
      }
      throw new IllegalStateException("Already notified", (Throwable)localObject);
    }
    this.J = true;
  }
  
  private <Data> s<R> l(com.bumptech.glide.load.data.d<?> paramd, Data paramData, DataSource paramDataSource)
    throws GlideException
  {
    if (paramData == null)
    {
      paramd.b();
      return null;
    }
    try
    {
      long l1 = f3.f.b();
      paramData = m(paramData, paramDataSource);
      if (Log.isLoggable("DecodeJob", 2))
      {
        paramDataSource = new java/lang/StringBuilder;
        paramDataSource.<init>();
        paramDataSource.append("Decoded result ");
        paramDataSource.append(paramData);
        t(paramDataSource.toString(), l1);
      }
      return paramData;
    }
    finally
    {
      paramd.b();
    }
  }
  
  private <Data> s<R> m(Data paramData, DataSource paramDataSource)
    throws GlideException
  {
    return E(paramData, paramDataSource, this.a.h(paramData.getClass()));
  }
  
  private void n()
  {
    if (Log.isLoggable("DecodeJob", 2))
    {
      long l1 = this.w;
      localObject = new StringBuilder();
      ((StringBuilder)localObject).append("data: ");
      ((StringBuilder)localObject).append(this.F);
      ((StringBuilder)localObject).append(", cache key: ");
      ((StringBuilder)localObject).append(this.D);
      ((StringBuilder)localObject).append(", fetcher: ");
      ((StringBuilder)localObject).append(this.H);
      u("Retrieved data", l1, ((StringBuilder)localObject).toString());
    }
    Object localObject = null;
    try
    {
      s locals = l(this.H, this.F, this.G);
      localObject = locals;
    }
    catch (GlideException localGlideException)
    {
      localGlideException.setLoggingDetails(this.E, this.G);
      this.b.add(localGlideException);
    }
    if (localObject != null) {
      w((s)localObject, this.G, this.L);
    } else {
      D();
    }
  }
  
  private e o()
  {
    int i1 = a.b[this.r.ordinal()];
    if (i1 != 1)
    {
      if (i1 != 2)
      {
        if (i1 != 3)
        {
          if (i1 == 4) {
            return null;
          }
          StringBuilder localStringBuilder = new StringBuilder();
          localStringBuilder.append("Unrecognized stage: ");
          localStringBuilder.append(this.r);
          throw new IllegalStateException(localStringBuilder.toString());
        }
        return new w(this.a, this);
      }
      return new b(this.a, this);
    }
    return new t(this.a, this);
  }
  
  private Stage p(Stage paramStage)
  {
    int i1 = a.b[paramStage.ordinal()];
    if (i1 != 1)
    {
      if (i1 != 2)
      {
        if ((i1 != 3) && (i1 != 4))
        {
          if (i1 == 5)
          {
            if (this.n.b()) {
              paramStage = Stage.RESOURCE_CACHE;
            } else {
              paramStage = p(Stage.RESOURCE_CACHE);
            }
            return paramStage;
          }
          StringBuilder localStringBuilder = new StringBuilder();
          localStringBuilder.append("Unrecognized stage: ");
          localStringBuilder.append(paramStage);
          throw new IllegalArgumentException(localStringBuilder.toString());
        }
        return Stage.FINISHED;
      }
      if (this.x) {
        paramStage = Stage.FINISHED;
      } else {
        paramStage = Stage.SOURCE;
      }
      return paramStage;
    }
    if (this.n.a()) {
      paramStage = Stage.DATA_CACHE;
    } else {
      paramStage = p(Stage.DATA_CACHE);
    }
    return paramStage;
  }
  
  private n2.d q(DataSource paramDataSource)
  {
    n2.d locald = this.o;
    boolean bool;
    if ((paramDataSource != DataSource.RESOURCE_DISK_CACHE) && (!this.a.w())) {
      bool = false;
    } else {
      bool = true;
    }
    paramDataSource = com.bumptech.glide.load.resource.bitmap.l.j;
    Boolean localBoolean = (Boolean)locald.c(paramDataSource);
    if ((localBoolean != null) && ((!localBoolean.booleanValue()) || (bool))) {
      return locald;
    }
    locald = new n2.d();
    locald.d(this.o);
    locald.e(paramDataSource, Boolean.valueOf(bool));
    return locald;
  }
  
  private int r()
  {
    return this.j.ordinal();
  }
  
  private void t(String paramString, long paramLong)
  {
    u(paramString, paramLong, null);
  }
  
  private void u(String paramString1, long paramLong, String paramString2)
  {
    StringBuilder localStringBuilder = new StringBuilder();
    localStringBuilder.append(paramString1);
    localStringBuilder.append(" in ");
    localStringBuilder.append(f3.f.a(paramLong));
    localStringBuilder.append(", load key: ");
    localStringBuilder.append(this.k);
    if (paramString2 != null)
    {
      paramString1 = new StringBuilder();
      paramString1.append(", ");
      paramString1.append(paramString2);
      paramString1 = paramString1.toString();
    }
    else
    {
      paramString1 = "";
    }
    localStringBuilder.append(paramString1);
    localStringBuilder.append(", thread: ");
    localStringBuilder.append(Thread.currentThread().getName());
    Log.v("DecodeJob", localStringBuilder.toString());
  }
  
  private void v(s<R> params, DataSource paramDataSource, boolean paramBoolean)
  {
    G();
    this.p.c(params, paramDataSource, paramBoolean);
  }
  
  private void w(s<R> params, DataSource paramDataSource, boolean paramBoolean)
  {
    if ((params instanceof o)) {
      ((o)params).c();
    }
    Object localObject1 = null;
    Object localObject2 = params;
    if (this.f.c())
    {
      localObject2 = r.e(params);
      localObject1 = localObject2;
    }
    v((s)localObject2, paramDataSource, paramBoolean);
    this.r = Stage.ENCODE;
    try
    {
      if (this.f.c()) {
        this.f.b(this.d, this.o);
      }
      if (localObject1 != null) {
        localObject1.g();
      }
      y();
      return;
    }
    finally
    {
      if (localObject1 != null) {
        localObject1.g();
      }
    }
  }
  
  private void x()
  {
    G();
    GlideException localGlideException = new GlideException("Failed to load resource", new ArrayList(this.b));
    this.p.a(localGlideException);
    z();
  }
  
  private void y()
  {
    if (this.g.b()) {
      C();
    }
  }
  
  private void z()
  {
    if (this.g.c()) {
      C();
    }
  }
  
  <Z> s<Z> A(DataSource paramDataSource, s<Z> params)
  {
    Class localClass = params.get().getClass();
    Object localObject1 = DataSource.RESOURCE_DISK_CACHE;
    Object localObject2 = null;
    g localg;
    if (paramDataSource != localObject1)
    {
      localg = this.a.r(localClass);
      localObject1 = localg.b(this.h, params, this.l, this.m);
    }
    else
    {
      localObject1 = params;
      localg = null;
    }
    if (!params.equals(localObject1)) {
      params.a();
    }
    EncodeStrategy localEncodeStrategy;
    if (this.a.v((s)localObject1))
    {
      params = this.a.n((s)localObject1);
      localEncodeStrategy = params.a(this.o);
    }
    else
    {
      localEncodeStrategy = EncodeStrategy.NONE;
      params = (s<Z>)localObject2;
    }
    boolean bool = this.a.x(this.D);
    localObject2 = localObject1;
    if (this.n.d(bool ^ true, paramDataSource, localEncodeStrategy)) {
      if (params != null)
      {
        int i1 = a.c[localEncodeStrategy.ordinal()];
        if (i1 != 1)
        {
          if (i1 == 2)
          {
            paramDataSource = new u(this.a.b(), this.D, this.i, this.l, this.m, localg, localClass, this.o);
          }
          else
          {
            paramDataSource = new StringBuilder();
            paramDataSource.append("Unknown strategy: ");
            paramDataSource.append(localEncodeStrategy);
            throw new IllegalArgumentException(paramDataSource.toString());
          }
        }
        else {
          paramDataSource = new c(this.D, this.i);
        }
        localObject2 = r.e((s)localObject1);
        this.f.d(paramDataSource, params, (r)localObject2);
      }
      else
      {
        throw new Registry.NoResultEncoderAvailableException(((s)localObject1).get().getClass());
      }
    }
    return localObject2;
  }
  
  void B(boolean paramBoolean)
  {
    if (this.g.d(paramBoolean)) {
      C();
    }
  }
  
  boolean H()
  {
    Stage localStage = p(Stage.INITIALIZE);
    boolean bool;
    if ((localStage != Stage.RESOURCE_CACHE) && (localStage != Stage.DATA_CACHE)) {
      bool = false;
    } else {
      bool = true;
    }
    return bool;
  }
  
  public void b(n2.b paramb1, Object paramObject, com.bumptech.glide.load.data.d<?> paramd, DataSource paramDataSource, n2.b paramb2)
  {
    this.D = paramb1;
    this.F = paramObject;
    this.H = paramd;
    this.G = paramDataSource;
    this.E = paramb2;
    paramObject = this.a.c();
    boolean bool = false;
    if (paramb1 != paramObject.get(0)) {
      bool = true;
    }
    this.L = bool;
    if (Thread.currentThread() != this.z)
    {
      this.v = RunReason.DECODE_DATA;
      this.p.d(this);
    }
    else
    {
      g3.b.a("DecodeJob.decodeFromRetrievedData");
    }
    try
    {
      n();
      return;
    }
    finally
    {
      g3.b.d();
    }
  }
  
  public void c()
  {
    this.v = RunReason.SWITCH_TO_SOURCE_SERVICE;
    this.p.d(this);
  }
  
  public g3.c h()
  {
    return this.c;
  }
  
  public void i(n2.b paramb, Exception paramException, com.bumptech.glide.load.data.d<?> paramd, DataSource paramDataSource)
  {
    paramd.b();
    paramException = new GlideException("Fetching data failed", paramException);
    paramException.setLoggingDetails(paramb, paramDataSource, paramd.a());
    this.b.add(paramException);
    if (Thread.currentThread() != this.z)
    {
      this.v = RunReason.SWITCH_TO_SOURCE_SERVICE;
      this.p.d(this);
    }
    else
    {
      D();
    }
  }
  
  public void j()
  {
    this.K = true;
    e locale = this.I;
    if (locale != null) {
      locale.cancel();
    }
  }
  
  public int k(DecodeJob<?> paramDecodeJob)
  {
    int i1 = r() - paramDecodeJob.r();
    int i2 = i1;
    if (i1 == 0) {
      i2 = this.q - paramDecodeJob.q;
    }
    return i2;
  }
  
  /* Error */
  public void run()
  {
    // Byte code:
    //   0: ldc_w 614
    //   3: aload_0
    //   4: getfield 166	com/bumptech/glide/load/engine/DecodeJob:y	Ljava/lang/Object;
    //   7: invokestatic 617	g3/b:b	(Ljava/lang/String;Ljava/lang/Object;)V
    //   10: aload_0
    //   11: getfield 160	com/bumptech/glide/load/engine/DecodeJob:H	Lcom/bumptech/glide/load/data/d;
    //   14: astore_1
    //   15: aload_0
    //   16: getfield 164	com/bumptech/glide/load/engine/DecodeJob:K	Z
    //   19: ifeq +21 -> 40
    //   22: aload_0
    //   23: invokespecial 208	com/bumptech/glide/load/engine/DecodeJob:x	()V
    //   26: aload_1
    //   27: ifnull +9 -> 36
    //   30: aload_1
    //   31: invokeinterface 303 1 0
    //   36: invokestatic 582	g3/b:d	()V
    //   39: return
    //   40: aload_0
    //   41: invokespecial 619	com/bumptech/glide/load/engine/DecodeJob:F	()V
    //   44: aload_1
    //   45: ifnull +9 -> 54
    //   48: aload_1
    //   49: invokeinterface 303 1 0
    //   54: invokestatic 582	g3/b:d	()V
    //   57: return
    //   58: astore_2
    //   59: ldc_w 308
    //   62: iconst_3
    //   63: invokestatic 314	android/util/Log:isLoggable	(Ljava/lang/String;I)Z
    //   66: ifeq +57 -> 123
    //   69: new 257	java/lang/StringBuilder
    //   72: astore_3
    //   73: aload_3
    //   74: invokespecial 258	java/lang/StringBuilder:<init>	()V
    //   77: aload_3
    //   78: ldc_w 621
    //   81: invokevirtual 264	java/lang/StringBuilder:append	(Ljava/lang/String;)Ljava/lang/StringBuilder;
    //   84: pop
    //   85: aload_3
    //   86: aload_0
    //   87: getfield 164	com/bumptech/glide/load/engine/DecodeJob:K	Z
    //   90: invokevirtual 624	java/lang/StringBuilder:append	(Z)Ljava/lang/StringBuilder;
    //   93: pop
    //   94: aload_3
    //   95: ldc_w 626
    //   98: invokevirtual 264	java/lang/StringBuilder:append	(Ljava/lang/String;)Ljava/lang/StringBuilder;
    //   101: pop
    //   102: aload_3
    //   103: aload_0
    //   104: getfield 148	com/bumptech/glide/load/engine/DecodeJob:r	Lcom/bumptech/glide/load/engine/DecodeJob$Stage;
    //   107: invokevirtual 267	java/lang/StringBuilder:append	(Ljava/lang/Object;)Ljava/lang/StringBuilder;
    //   110: pop
    //   111: ldc_w 308
    //   114: aload_3
    //   115: invokevirtual 273	java/lang/StringBuilder:toString	()Ljava/lang/String;
    //   118: aload_2
    //   119: invokestatic 629	android/util/Log:d	(Ljava/lang/String;Ljava/lang/String;Ljava/lang/Throwable;)I
    //   122: pop
    //   123: aload_0
    //   124: getfield 148	com/bumptech/glide/load/engine/DecodeJob:r	Lcom/bumptech/glide/load/engine/DecodeJob$Stage;
    //   127: getstatic 467	com/bumptech/glide/load/engine/DecodeJob$Stage:ENCODE	Lcom/bumptech/glide/load/engine/DecodeJob$Stage;
    //   130: if_acmpeq +18 -> 148
    //   133: aload_0
    //   134: getfield 106	com/bumptech/glide/load/engine/DecodeJob:b	Ljava/util/List;
    //   137: aload_2
    //   138: invokeinterface 354 2 0
    //   143: pop
    //   144: aload_0
    //   145: invokespecial 208	com/bumptech/glide/load/engine/DecodeJob:x	()V
    //   148: aload_0
    //   149: getfield 164	com/bumptech/glide/load/engine/DecodeJob:K	Z
    //   152: ifne +5 -> 157
    //   155: aload_2
    //   156: athrow
    //   157: aload_2
    //   158: athrow
    //   159: astore_2
    //   160: aload_2
    //   161: athrow
    //   162: astore_2
    //   163: aload_1
    //   164: ifnull +9 -> 173
    //   167: aload_1
    //   168: invokeinterface 303 1 0
    //   173: invokestatic 582	g3/b:d	()V
    //   176: aload_2
    //   177: athrow
    // Local variable table:
    //   start	length	slot	name	signature
    //   0	178	0	this	DecodeJob
    //   14	154	1	locald	com.bumptech.glide.load.data.d
    //   58	100	2	localThrowable	Throwable
    //   159	2	2	localCallbackException	CallbackException
    //   162	15	2	localObject	Object
    //   72	43	3	localStringBuilder	StringBuilder
    // Exception table:
    //   from	to	target	type
    //   15	26	58	finally
    //   40	44	58	finally
    //   15	26	159	com/bumptech/glide/load/engine/CallbackException
    //   40	44	159	com/bumptech/glide/load/engine/CallbackException
    //   59	123	162	finally
    //   123	148	162	finally
    //   148	157	162	finally
    //   157	159	162	finally
    //   160	162	162	finally
  }
  
  DecodeJob<R> s(com.bumptech.glide.d paramd, Object paramObject, l paraml, n2.b paramb, int paramInt1, int paramInt2, Class<?> paramClass, Class<R> paramClass1, Priority paramPriority, h paramh, Map<Class<?>, g<?>> paramMap, boolean paramBoolean1, boolean paramBoolean2, boolean paramBoolean3, n2.d paramd1, b<R> paramb1, int paramInt3)
  {
    this.a.u(paramd, paramObject, paramb, paramInt1, paramInt2, paramh, paramClass, paramClass1, paramPriority, paramd1, paramMap, paramBoolean1, paramBoolean2, this.d);
    this.h = paramd;
    this.i = paramb;
    this.j = paramPriority;
    this.k = paraml;
    this.l = paramInt1;
    this.m = paramInt2;
    this.n = paramh;
    this.x = paramBoolean3;
    this.o = paramd1;
    this.p = paramb1;
    this.q = paramInt3;
    this.v = RunReason.INITIALIZE;
    this.y = paramObject;
    return this;
  }
  
  private static enum RunReason
  {
    static
    {
      RunReason localRunReason1 = new RunReason("INITIALIZE", 0);
      INITIALIZE = localRunReason1;
      RunReason localRunReason2 = new RunReason("SWITCH_TO_SOURCE_SERVICE", 1);
      SWITCH_TO_SOURCE_SERVICE = localRunReason2;
      RunReason localRunReason3 = new RunReason("DECODE_DATA", 2);
      DECODE_DATA = localRunReason3;
      $VALUES = new RunReason[] { localRunReason1, localRunReason2, localRunReason3 };
    }
    
    private RunReason() {}
  }
  
  private static enum Stage
  {
    static
    {
      Stage localStage1 = new Stage("INITIALIZE", 0);
      INITIALIZE = localStage1;
      Stage localStage2 = new Stage("RESOURCE_CACHE", 1);
      RESOURCE_CACHE = localStage2;
      Stage localStage3 = new Stage("DATA_CACHE", 2);
      DATA_CACHE = localStage3;
      Stage localStage4 = new Stage("SOURCE", 3);
      SOURCE = localStage4;
      Stage localStage5 = new Stage("ENCODE", 4);
      ENCODE = localStage5;
      Stage localStage6 = new Stage("FINISHED", 5);
      FINISHED = localStage6;
      $VALUES = new Stage[] { localStage1, localStage2, localStage3, localStage4, localStage5, localStage6 };
    }
    
    private Stage() {}
  }
  
  static abstract interface b<R>
  {
    public abstract void a(GlideException paramGlideException);
    
    public abstract void c(s<R> params, DataSource paramDataSource, boolean paramBoolean);
    
    public abstract void d(DecodeJob<?> paramDecodeJob);
  }
  
  private final class c<Z>
    implements g.a<Z>
  {
    private final DataSource a;
    
    c(DataSource paramDataSource)
    {
      this.a = paramDataSource;
    }
    
    public s<Z> a(s<Z> params)
    {
      return DecodeJob.this.A(this.a, params);
    }
  }
  
  private static class d<Z>
  {
    private n2.b a;
    private n2.f<Z> b;
    private r<Z> c;
    
    void a()
    {
      this.a = null;
      this.b = null;
      this.c = null;
    }
    
    void b(DecodeJob.e parame, n2.d paramd)
    {
      g3.b.a("DecodeJob.encode");
      try
      {
        a locala = parame.a();
        parame = this.a;
        d locald = new com/bumptech/glide/load/engine/d;
        locald.<init>(this.b, this.c, paramd);
        locala.b(parame, locald);
        return;
      }
      finally
      {
        this.c.g();
        g3.b.d();
      }
    }
    
    boolean c()
    {
      boolean bool;
      if (this.c != null) {
        bool = true;
      } else {
        bool = false;
      }
      return bool;
    }
    
    <X> void d(n2.b paramb, n2.f<X> paramf, r<X> paramr)
    {
      this.a = paramb;
      this.b = paramf;
      this.c = paramr;
    }
  }
  
  static abstract interface e
  {
    public abstract a a();
  }
  
  private static class f
  {
    private boolean a;
    private boolean b;
    private boolean c;
    
    private boolean a(boolean paramBoolean)
    {
      if (((this.c) || (paramBoolean) || (this.b)) && (this.a)) {
        paramBoolean = true;
      } else {
        paramBoolean = false;
      }
      return paramBoolean;
    }
    
    boolean b()
    {
      try
      {
        this.b = true;
        boolean bool = a(false);
        return bool;
      }
      finally
      {
        localObject = finally;
        throw localObject;
      }
    }
    
    boolean c()
    {
      try
      {
        this.c = true;
        boolean bool = a(false);
        return bool;
      }
      finally
      {
        localObject = finally;
        throw localObject;
      }
    }
    
    boolean d(boolean paramBoolean)
    {
      try
      {
        this.a = true;
        paramBoolean = a(paramBoolean);
        return paramBoolean;
      }
      finally
      {
        localObject = finally;
        throw localObject;
      }
    }
    
    void e()
    {
      try
      {
        this.b = false;
        this.a = false;
        this.c = false;
        return;
      }
      finally
      {
        localObject = finally;
        throw localObject;
      }
    }
  }
}


/* Location:           J:\AndroidKiller_v1.3.1\AndroidKiller_v1.3.1\projects\小米日历-v13.18.0.0\ProjectSrc\smali\
 * Qualified Name:     com.bumptech.glide.load.engine.DecodeJob
 * JD-Core Version:    0.7.0.1
 */