package e6;

import android.content.Context;
import android.content.SharedPreferences;
import android.content.SharedPreferences.Editor;
import com.xiaomi.analytics.Analytics;
import f6.a;
import f6.b;
import f6.h;
import f6.l;
import f6.m;
import f6.n;
import java.util.Date;
import java.util.Random;

class d
{
  private static final long i = m.a;
  private static volatile d j;
  private Context a;
  private String b = "";
  private String c = "";
  private String d;
  private int e;
  private c f;
  private Runnable g = new a();
  private Runnable h = new b();
  
  private d(Context paramContext)
  {
    this.a = b.a(paramContext);
  }
  
  public static d n(Context paramContext)
  {
    try
    {
      if (j == null)
      {
        d locald = new e6/d;
        locald.<init>(paramContext);
        j = locald;
      }
      paramContext = j;
      return paramContext;
    }
    finally {}
  }
  
  private long o()
  {
    try
    {
      long l = this.a.getSharedPreferences("analytics_updater", 0).getLong("updateTime", 0L);
      return l;
    }
    finally
    {
      localObject = finally;
      throw localObject;
    }
  }
  
  private String p()
  {
    Random localRandom = new Random(System.nanoTime());
    try
    {
      String str = this.a.getPackageName();
      Object localObject = new java/lang/StringBuilder;
      ((StringBuilder)localObject).<init>();
      ((StringBuilder)localObject).append(str);
      ((StringBuilder)localObject).append(":");
      ((StringBuilder)localObject).append(localRandom.nextLong());
      localObject = n.a(((StringBuilder)localObject).toString());
      return localObject;
    }
    catch (Exception localException)
    {
      StringBuilder localStringBuilder = new StringBuilder();
      localStringBuilder.append(localRandom.nextLong());
      localStringBuilder.append("");
      return n.a(localStringBuilder.toString());
    }
  }
  
  private void r()
  {
    c localc = this.f;
    if (localc != null)
    {
      String str = this.d;
      int k = this.e;
      boolean bool = true;
      if (k != 1) {
        bool = false;
      }
      localc.a(str, bool);
    }
  }
  
  private long s(String paramString)
  {
    try
    {
      long l = Long.parseLong(paramString.split("-")[1]);
      return l;
    }
    catch (Exception paramString) {}
    return System.currentTimeMillis();
  }
  
  private void t(long paramLong)
  {
    try
    {
      SharedPreferences.Editor localEditor = this.a.getSharedPreferences("analytics_updater", 0).edit();
      localEditor.putLong("updateTime", paramLong);
      localEditor.apply();
      return;
    }
    finally
    {
      localObject = finally;
      throw localObject;
    }
  }
  
  public void m(String paramString)
  {
    if (h.g(this.a, "UpdateManager")) {
      return;
    }
    a.b("UpdateManager", "checkUpdate ");
    this.d = paramString;
    l.a(this.g);
    t(System.currentTimeMillis());
  }
  
  public boolean q()
  {
    if (h.g(this.a, "UpdateManager")) {
      return false;
    }
    if (!Analytics.isUpdateEnable())
    {
      a.b("UpdateManager", "Updating is disabled.");
      return false;
    }
    long l = o();
    StringBuilder localStringBuilder = new StringBuilder();
    localStringBuilder.append("last update check time is ");
    localStringBuilder.append(new Date(l).toString());
    a.b("UpdateManager", localStringBuilder.toString());
    return System.currentTimeMillis() - l >= i;
  }
  
  public void u(c paramc)
  {
    this.f = paramc;
  }
  
  class a
    implements Runnable
  {
    a() {}
    
    /* Error */
    public void run()
    {
      // Byte code:
      //   0: aload_0
      //   1: astore_1
      //   2: ldc 23
      //   4: astore_2
      //   5: ldc 25
      //   7: astore_3
      //   8: getstatic 30	e6/a:a	Le6/e;
      //   11: astore 4
      //   13: aload_1
      //   14: getfield 14	e6/d$a:a	Le6/d;
      //   17: invokestatic 33	e6/d:a	(Le6/d;)Landroid/content/Context;
      //   20: invokestatic 39	e6/c:F	(Landroid/content/Context;)Le6/c;
      //   23: invokevirtual 43	e6/c:L	()Le6/e;
      //   26: astore 5
      //   28: invokestatic 49	java/lang/System:currentTimeMillis	()J
      //   31: lstore 6
      //   33: iconst_0
      //   34: istore 8
      //   36: iload 8
      //   38: iconst_1
      //   39: iadd
      //   40: istore 9
      //   42: iload 8
      //   44: iconst_2
      //   45: if_icmpge +1339 -> 1384
      //   48: invokestatic 55	f6/j:b	()Ljava/lang/String;
      //   51: astore 10
      //   53: invokestatic 58	f6/j:f	()Ljava/lang/String;
      //   56: astore 11
      //   58: aload_1
      //   59: getfield 14	e6/d$a:a	Le6/d;
      //   62: invokestatic 33	e6/d:a	(Le6/d;)Landroid/content/Context;
      //   65: invokestatic 62	f6/j:d	(Landroid/content/Context;)Ljava/lang/String;
      //   68: astore 12
      //   70: invokestatic 65	f6/j:c	()Ljava/lang/String;
      //   73: astore 13
      //   75: aload_1
      //   76: getfield 14	e6/d$a:a	Le6/d;
      //   79: invokestatic 33	e6/d:a	(Le6/d;)Landroid/content/Context;
      //   82: invokestatic 70	f6/i:c	(Landroid/content/Context;)I
      //   85: istore 8
      //   87: aload_1
      //   88: getfield 14	e6/d$a:a	Le6/d;
      //   91: invokestatic 73	e6/d:b	(Le6/d;)Ljava/lang/String;
      //   94: astore 14
      //   96: aload_1
      //   97: getfield 14	e6/d$a:a	Le6/d;
      //   100: invokestatic 33	e6/d:a	(Le6/d;)Landroid/content/Context;
      //   103: invokevirtual 78	android/content/Context:getPackageName	()Ljava/lang/String;
      //   106: astore 15
      //   108: invokestatic 81	f6/j:h	()Ljava/lang/String;
      //   111: astore 16
      //   113: invokestatic 84	f6/j:g	()Ljava/lang/String;
      //   116: astore 17
      //   118: new 86	java/lang/StringBuilder
      //   121: astore_1
      //   122: aload_1
      //   123: invokespecial 87	java/lang/StringBuilder:<init>	()V
      //   126: new 86	java/lang/StringBuilder
      //   129: astore 18
      //   131: aload 18
      //   133: invokespecial 87	java/lang/StringBuilder:<init>	()V
      //   136: aload 18
      //   138: ldc 89
      //   140: invokevirtual 93	java/lang/StringBuilder:append	(Ljava/lang/String;)Ljava/lang/StringBuilder;
      //   143: pop
      //   144: aload 18
      //   146: aload 4
      //   148: invokevirtual 96	java/lang/StringBuilder:append	(Ljava/lang/Object;)Ljava/lang/StringBuilder;
      //   151: pop
      //   152: aload_1
      //   153: aload 18
      //   155: invokevirtual 99	java/lang/StringBuilder:toString	()Ljava/lang/String;
      //   158: invokevirtual 93	java/lang/StringBuilder:append	(Ljava/lang/String;)Ljava/lang/StringBuilder;
      //   161: pop
      //   162: new 86	java/lang/StringBuilder
      //   165: astore 18
      //   167: aload 18
      //   169: invokespecial 87	java/lang/StringBuilder:<init>	()V
      //   172: aload 18
      //   174: ldc 101
      //   176: invokevirtual 93	java/lang/StringBuilder:append	(Ljava/lang/String;)Ljava/lang/StringBuilder;
      //   179: pop
      //   180: aload 18
      //   182: aload 5
      //   184: invokevirtual 96	java/lang/StringBuilder:append	(Ljava/lang/Object;)Ljava/lang/StringBuilder;
      //   187: pop
      //   188: aload_1
      //   189: aload 18
      //   191: invokevirtual 99	java/lang/StringBuilder:toString	()Ljava/lang/String;
      //   194: invokevirtual 93	java/lang/StringBuilder:append	(Ljava/lang/String;)Ljava/lang/StringBuilder;
      //   197: pop
      //   198: new 86	java/lang/StringBuilder
      //   201: astore 18
      //   203: aload 18
      //   205: invokespecial 87	java/lang/StringBuilder:<init>	()V
      //   208: aload 18
      //   210: ldc 102
      //   212: invokevirtual 93	java/lang/StringBuilder:append	(Ljava/lang/String;)Ljava/lang/StringBuilder;
      //   215: pop
      //   216: aload 18
      //   218: aload 10
      //   220: invokevirtual 93	java/lang/StringBuilder:append	(Ljava/lang/String;)Ljava/lang/StringBuilder;
      //   223: pop
      //   224: aload_1
      //   225: aload 18
      //   227: invokevirtual 99	java/lang/StringBuilder:toString	()Ljava/lang/String;
      //   230: invokevirtual 93	java/lang/StringBuilder:append	(Ljava/lang/String;)Ljava/lang/StringBuilder;
      //   233: pop
      //   234: new 86	java/lang/StringBuilder
      //   237: astore 18
      //   239: aload 18
      //   241: invokespecial 87	java/lang/StringBuilder:<init>	()V
      //   244: aload 18
      //   246: ldc 103
      //   248: invokevirtual 93	java/lang/StringBuilder:append	(Ljava/lang/String;)Ljava/lang/StringBuilder;
      //   251: pop
      //   252: aload 18
      //   254: aload 11
      //   256: invokevirtual 93	java/lang/StringBuilder:append	(Ljava/lang/String;)Ljava/lang/StringBuilder;
      //   259: pop
      //   260: aload_1
      //   261: aload 18
      //   263: invokevirtual 99	java/lang/StringBuilder:toString	()Ljava/lang/String;
      //   266: invokevirtual 93	java/lang/StringBuilder:append	(Ljava/lang/String;)Ljava/lang/StringBuilder;
      //   269: pop
      //   270: invokestatic 109	f6/h:e	()Z
      //   273: ifne +39 -> 312
      //   276: new 86	java/lang/StringBuilder
      //   279: astore 18
      //   281: aload 18
      //   283: invokespecial 87	java/lang/StringBuilder:<init>	()V
      //   286: aload 18
      //   288: ldc 111
      //   290: invokevirtual 93	java/lang/StringBuilder:append	(Ljava/lang/String;)Ljava/lang/StringBuilder;
      //   293: pop
      //   294: aload 18
      //   296: aload 12
      //   298: invokevirtual 93	java/lang/StringBuilder:append	(Ljava/lang/String;)Ljava/lang/StringBuilder;
      //   301: pop
      //   302: aload_1
      //   303: aload 18
      //   305: invokevirtual 99	java/lang/StringBuilder:toString	()Ljava/lang/String;
      //   308: invokevirtual 93	java/lang/StringBuilder:append	(Ljava/lang/String;)Ljava/lang/StringBuilder;
      //   311: pop
      //   312: new 86	java/lang/StringBuilder
      //   315: astore 18
      //   317: aload 18
      //   319: invokespecial 87	java/lang/StringBuilder:<init>	()V
      //   322: aload 18
      //   324: ldc 113
      //   326: invokevirtual 93	java/lang/StringBuilder:append	(Ljava/lang/String;)Ljava/lang/StringBuilder;
      //   329: pop
      //   330: aload 18
      //   332: aload 13
      //   334: invokevirtual 93	java/lang/StringBuilder:append	(Ljava/lang/String;)Ljava/lang/StringBuilder;
      //   337: pop
      //   338: aload_1
      //   339: aload 18
      //   341: invokevirtual 99	java/lang/StringBuilder:toString	()Ljava/lang/String;
      //   344: invokevirtual 93	java/lang/StringBuilder:append	(Ljava/lang/String;)Ljava/lang/StringBuilder;
      //   347: pop
      //   348: new 86	java/lang/StringBuilder
      //   351: astore 18
      //   353: aload 18
      //   355: invokespecial 87	java/lang/StringBuilder:<init>	()V
      //   358: aload 18
      //   360: ldc 115
      //   362: invokevirtual 93	java/lang/StringBuilder:append	(Ljava/lang/String;)Ljava/lang/StringBuilder;
      //   365: pop
      //   366: aload 18
      //   368: iload 8
      //   370: invokevirtual 118	java/lang/StringBuilder:append	(I)Ljava/lang/StringBuilder;
      //   373: pop
      //   374: aload_1
      //   375: aload 18
      //   377: invokevirtual 99	java/lang/StringBuilder:toString	()Ljava/lang/String;
      //   380: invokevirtual 93	java/lang/StringBuilder:append	(Ljava/lang/String;)Ljava/lang/StringBuilder;
      //   383: pop
      //   384: new 86	java/lang/StringBuilder
      //   387: astore 18
      //   389: aload 18
      //   391: invokespecial 87	java/lang/StringBuilder:<init>	()V
      //   394: aload 18
      //   396: ldc 120
      //   398: invokevirtual 93	java/lang/StringBuilder:append	(Ljava/lang/String;)Ljava/lang/StringBuilder;
      //   401: pop
      //   402: aload 18
      //   404: aload 14
      //   406: invokevirtual 93	java/lang/StringBuilder:append	(Ljava/lang/String;)Ljava/lang/StringBuilder;
      //   409: pop
      //   410: aload_1
      //   411: aload 18
      //   413: invokevirtual 99	java/lang/StringBuilder:toString	()Ljava/lang/String;
      //   416: invokevirtual 93	java/lang/StringBuilder:append	(Ljava/lang/String;)Ljava/lang/StringBuilder;
      //   419: pop
      //   420: new 86	java/lang/StringBuilder
      //   423: astore 18
      //   425: aload 18
      //   427: invokespecial 87	java/lang/StringBuilder:<init>	()V
      //   430: aload 18
      //   432: ldc 122
      //   434: invokevirtual 93	java/lang/StringBuilder:append	(Ljava/lang/String;)Ljava/lang/StringBuilder;
      //   437: pop
      //   438: aload 18
      //   440: aload 15
      //   442: invokevirtual 93	java/lang/StringBuilder:append	(Ljava/lang/String;)Ljava/lang/StringBuilder;
      //   445: pop
      //   446: aload_1
      //   447: aload 18
      //   449: invokevirtual 99	java/lang/StringBuilder:toString	()Ljava/lang/String;
      //   452: invokevirtual 93	java/lang/StringBuilder:append	(Ljava/lang/String;)Ljava/lang/StringBuilder;
      //   455: pop
      //   456: new 86	java/lang/StringBuilder
      //   459: astore 18
      //   461: aload 18
      //   463: invokespecial 87	java/lang/StringBuilder:<init>	()V
      //   466: aload 18
      //   468: ldc 124
      //   470: invokevirtual 93	java/lang/StringBuilder:append	(Ljava/lang/String;)Ljava/lang/StringBuilder;
      //   473: pop
      //   474: aload 18
      //   476: aload 16
      //   478: invokevirtual 93	java/lang/StringBuilder:append	(Ljava/lang/String;)Ljava/lang/StringBuilder;
      //   481: pop
      //   482: aload_1
      //   483: aload 18
      //   485: invokevirtual 99	java/lang/StringBuilder:toString	()Ljava/lang/String;
      //   488: invokevirtual 93	java/lang/StringBuilder:append	(Ljava/lang/String;)Ljava/lang/StringBuilder;
      //   491: pop
      //   492: new 86	java/lang/StringBuilder
      //   495: astore 18
      //   497: aload 18
      //   499: invokespecial 87	java/lang/StringBuilder:<init>	()V
      //   502: aload 18
      //   504: ldc 126
      //   506: invokevirtual 93	java/lang/StringBuilder:append	(Ljava/lang/String;)Ljava/lang/StringBuilder;
      //   509: pop
      //   510: aload 18
      //   512: lload 6
      //   514: invokevirtual 129	java/lang/StringBuilder:append	(J)Ljava/lang/StringBuilder;
      //   517: pop
      //   518: aload_1
      //   519: aload 18
      //   521: invokevirtual 99	java/lang/StringBuilder:toString	()Ljava/lang/String;
      //   524: invokevirtual 93	java/lang/StringBuilder:append	(Ljava/lang/String;)Ljava/lang/StringBuilder;
      //   527: pop
      //   528: new 86	java/lang/StringBuilder
      //   531: astore 18
      //   533: aload 18
      //   535: invokespecial 87	java/lang/StringBuilder:<init>	()V
      //   538: aload 18
      //   540: aload_2
      //   541: invokevirtual 93	java/lang/StringBuilder:append	(Ljava/lang/String;)Ljava/lang/StringBuilder;
      //   544: pop
      //   545: aload 18
      //   547: aload 17
      //   549: invokevirtual 93	java/lang/StringBuilder:append	(Ljava/lang/String;)Ljava/lang/StringBuilder;
      //   552: pop
      //   553: aload_1
      //   554: aload 18
      //   556: invokevirtual 99	java/lang/StringBuilder:toString	()Ljava/lang/String;
      //   559: invokevirtual 93	java/lang/StringBuilder:append	(Ljava/lang/String;)Ljava/lang/StringBuilder;
      //   562: pop
      //   563: aload_1
      //   564: ldc 131
      //   566: invokevirtual 93	java/lang/StringBuilder:append	(Ljava/lang/String;)Ljava/lang/StringBuilder;
      //   569: pop
      //   570: aload_1
      //   571: invokevirtual 99	java/lang/StringBuilder:toString	()Ljava/lang/String;
      //   574: invokestatic 136	f6/n:a	(Ljava/lang/String;)Ljava/lang/String;
      //   577: astore 19
      //   579: new 86	java/lang/StringBuilder
      //   582: astore 18
      //   584: invokestatic 109	f6/h:e	()Z
      //   587: ifeq +9 -> 596
      //   590: ldc 138
      //   592: astore_1
      //   593: goto +6 -> 599
      //   596: ldc 140
      //   598: astore_1
      //   599: aload 18
      //   601: aload_1
      //   602: invokespecial 143	java/lang/StringBuilder:<init>	(Ljava/lang/String;)V
      //   605: new 86	java/lang/StringBuilder
      //   608: astore_1
      //   609: aload_1
      //   610: invokespecial 87	java/lang/StringBuilder:<init>	()V
      //   613: aload_1
      //   614: ldc 145
      //   616: invokevirtual 93	java/lang/StringBuilder:append	(Ljava/lang/String;)Ljava/lang/StringBuilder;
      //   619: pop
      //   620: aload_1
      //   621: aload 4
      //   623: invokevirtual 96	java/lang/StringBuilder:append	(Ljava/lang/Object;)Ljava/lang/StringBuilder;
      //   626: pop
      //   627: aload 18
      //   629: aload_1
      //   630: invokevirtual 99	java/lang/StringBuilder:toString	()Ljava/lang/String;
      //   633: invokevirtual 93	java/lang/StringBuilder:append	(Ljava/lang/String;)Ljava/lang/StringBuilder;
      //   636: pop
      //   637: new 86	java/lang/StringBuilder
      //   640: astore_1
      //   641: aload_1
      //   642: invokespecial 87	java/lang/StringBuilder:<init>	()V
      //   645: aload_1
      //   646: ldc 147
      //   648: invokevirtual 93	java/lang/StringBuilder:append	(Ljava/lang/String;)Ljava/lang/StringBuilder;
      //   651: pop
      //   652: aload_1
      //   653: aload 5
      //   655: invokevirtual 96	java/lang/StringBuilder:append	(Ljava/lang/Object;)Ljava/lang/StringBuilder;
      //   658: pop
      //   659: aload 18
      //   661: aload_1
      //   662: invokevirtual 99	java/lang/StringBuilder:toString	()Ljava/lang/String;
      //   665: invokevirtual 93	java/lang/StringBuilder:append	(Ljava/lang/String;)Ljava/lang/StringBuilder;
      //   668: pop
      //   669: new 86	java/lang/StringBuilder
      //   672: astore_1
      //   673: aload_1
      //   674: invokespecial 87	java/lang/StringBuilder:<init>	()V
      //   677: aload_1
      //   678: ldc 149
      //   680: invokevirtual 93	java/lang/StringBuilder:append	(Ljava/lang/String;)Ljava/lang/StringBuilder;
      //   683: pop
      //   684: aload_1
      //   685: aload 10
      //   687: invokevirtual 93	java/lang/StringBuilder:append	(Ljava/lang/String;)Ljava/lang/StringBuilder;
      //   690: pop
      //   691: aload 18
      //   693: aload_1
      //   694: invokevirtual 99	java/lang/StringBuilder:toString	()Ljava/lang/String;
      //   697: invokevirtual 93	java/lang/StringBuilder:append	(Ljava/lang/String;)Ljava/lang/StringBuilder;
      //   700: pop
      //   701: new 86	java/lang/StringBuilder
      //   704: astore_1
      //   705: aload_1
      //   706: invokespecial 87	java/lang/StringBuilder:<init>	()V
      //   709: aload_1
      //   710: ldc 151
      //   712: invokevirtual 93	java/lang/StringBuilder:append	(Ljava/lang/String;)Ljava/lang/StringBuilder;
      //   715: pop
      //   716: aload_1
      //   717: aload 11
      //   719: invokevirtual 93	java/lang/StringBuilder:append	(Ljava/lang/String;)Ljava/lang/StringBuilder;
      //   722: pop
      //   723: aload 18
      //   725: aload_1
      //   726: invokevirtual 99	java/lang/StringBuilder:toString	()Ljava/lang/String;
      //   729: invokevirtual 93	java/lang/StringBuilder:append	(Ljava/lang/String;)Ljava/lang/StringBuilder;
      //   732: pop
      //   733: invokestatic 109	f6/h:e	()Z
      //   736: ifne +35 -> 771
      //   739: new 86	java/lang/StringBuilder
      //   742: astore_1
      //   743: aload_1
      //   744: invokespecial 87	java/lang/StringBuilder:<init>	()V
      //   747: aload_1
      //   748: ldc 153
      //   750: invokevirtual 93	java/lang/StringBuilder:append	(Ljava/lang/String;)Ljava/lang/StringBuilder;
      //   753: pop
      //   754: aload_1
      //   755: aload 12
      //   757: invokevirtual 93	java/lang/StringBuilder:append	(Ljava/lang/String;)Ljava/lang/StringBuilder;
      //   760: pop
      //   761: aload 18
      //   763: aload_1
      //   764: invokevirtual 99	java/lang/StringBuilder:toString	()Ljava/lang/String;
      //   767: invokevirtual 93	java/lang/StringBuilder:append	(Ljava/lang/String;)Ljava/lang/StringBuilder;
      //   770: pop
      //   771: new 86	java/lang/StringBuilder
      //   774: astore_1
      //   775: aload_1
      //   776: invokespecial 87	java/lang/StringBuilder:<init>	()V
      //   779: aload_1
      //   780: ldc 155
      //   782: invokevirtual 93	java/lang/StringBuilder:append	(Ljava/lang/String;)Ljava/lang/StringBuilder;
      //   785: pop
      //   786: aload_1
      //   787: aload 13
      //   789: invokevirtual 93	java/lang/StringBuilder:append	(Ljava/lang/String;)Ljava/lang/StringBuilder;
      //   792: pop
      //   793: aload 18
      //   795: aload_1
      //   796: invokevirtual 99	java/lang/StringBuilder:toString	()Ljava/lang/String;
      //   799: invokevirtual 93	java/lang/StringBuilder:append	(Ljava/lang/String;)Ljava/lang/StringBuilder;
      //   802: pop
      //   803: new 86	java/lang/StringBuilder
      //   806: astore_1
      //   807: aload_1
      //   808: invokespecial 87	java/lang/StringBuilder:<init>	()V
      //   811: aload_1
      //   812: ldc 157
      //   814: invokevirtual 93	java/lang/StringBuilder:append	(Ljava/lang/String;)Ljava/lang/StringBuilder;
      //   817: pop
      //   818: aload_1
      //   819: iload 8
      //   821: invokevirtual 118	java/lang/StringBuilder:append	(I)Ljava/lang/StringBuilder;
      //   824: pop
      //   825: aload 18
      //   827: aload_1
      //   828: invokevirtual 99	java/lang/StringBuilder:toString	()Ljava/lang/String;
      //   831: invokevirtual 93	java/lang/StringBuilder:append	(Ljava/lang/String;)Ljava/lang/StringBuilder;
      //   834: pop
      //   835: new 86	java/lang/StringBuilder
      //   838: astore_1
      //   839: aload_1
      //   840: invokespecial 87	java/lang/StringBuilder:<init>	()V
      //   843: aload_1
      //   844: ldc 159
      //   846: invokevirtual 93	java/lang/StringBuilder:append	(Ljava/lang/String;)Ljava/lang/StringBuilder;
      //   849: pop
      //   850: aload_1
      //   851: aload 14
      //   853: invokevirtual 93	java/lang/StringBuilder:append	(Ljava/lang/String;)Ljava/lang/StringBuilder;
      //   856: pop
      //   857: aload 18
      //   859: aload_1
      //   860: invokevirtual 99	java/lang/StringBuilder:toString	()Ljava/lang/String;
      //   863: invokevirtual 93	java/lang/StringBuilder:append	(Ljava/lang/String;)Ljava/lang/StringBuilder;
      //   866: pop
      //   867: new 86	java/lang/StringBuilder
      //   870: astore_1
      //   871: aload_1
      //   872: invokespecial 87	java/lang/StringBuilder:<init>	()V
      //   875: aload_1
      //   876: ldc 161
      //   878: invokevirtual 93	java/lang/StringBuilder:append	(Ljava/lang/String;)Ljava/lang/StringBuilder;
      //   881: pop
      //   882: aload_1
      //   883: aload 15
      //   885: invokevirtual 93	java/lang/StringBuilder:append	(Ljava/lang/String;)Ljava/lang/StringBuilder;
      //   888: pop
      //   889: aload 18
      //   891: aload_1
      //   892: invokevirtual 99	java/lang/StringBuilder:toString	()Ljava/lang/String;
      //   895: invokevirtual 93	java/lang/StringBuilder:append	(Ljava/lang/String;)Ljava/lang/StringBuilder;
      //   898: pop
      //   899: new 86	java/lang/StringBuilder
      //   902: astore_1
      //   903: aload_1
      //   904: invokespecial 87	java/lang/StringBuilder:<init>	()V
      //   907: aload_1
      //   908: ldc 163
      //   910: invokevirtual 93	java/lang/StringBuilder:append	(Ljava/lang/String;)Ljava/lang/StringBuilder;
      //   913: pop
      //   914: aload_1
      //   915: aload 16
      //   917: invokevirtual 93	java/lang/StringBuilder:append	(Ljava/lang/String;)Ljava/lang/StringBuilder;
      //   920: pop
      //   921: aload 18
      //   923: aload_1
      //   924: invokevirtual 99	java/lang/StringBuilder:toString	()Ljava/lang/String;
      //   927: invokevirtual 93	java/lang/StringBuilder:append	(Ljava/lang/String;)Ljava/lang/StringBuilder;
      //   930: pop
      //   931: new 86	java/lang/StringBuilder
      //   934: astore_1
      //   935: aload_1
      //   936: invokespecial 87	java/lang/StringBuilder:<init>	()V
      //   939: aload_1
      //   940: ldc 165
      //   942: invokevirtual 93	java/lang/StringBuilder:append	(Ljava/lang/String;)Ljava/lang/StringBuilder;
      //   945: pop
      //   946: aload_1
      //   947: lload 6
      //   949: invokevirtual 129	java/lang/StringBuilder:append	(J)Ljava/lang/StringBuilder;
      //   952: pop
      //   953: aload 18
      //   955: aload_1
      //   956: invokevirtual 99	java/lang/StringBuilder:toString	()Ljava/lang/String;
      //   959: invokevirtual 93	java/lang/StringBuilder:append	(Ljava/lang/String;)Ljava/lang/StringBuilder;
      //   962: pop
      //   963: new 86	java/lang/StringBuilder
      //   966: astore_1
      //   967: aload_1
      //   968: invokespecial 87	java/lang/StringBuilder:<init>	()V
      //   971: aload_1
      //   972: ldc 167
      //   974: invokevirtual 93	java/lang/StringBuilder:append	(Ljava/lang/String;)Ljava/lang/StringBuilder;
      //   977: pop
      //   978: aload_1
      //   979: aload 17
      //   981: invokevirtual 93	java/lang/StringBuilder:append	(Ljava/lang/String;)Ljava/lang/StringBuilder;
      //   984: pop
      //   985: aload 18
      //   987: aload_1
      //   988: invokevirtual 99	java/lang/StringBuilder:toString	()Ljava/lang/String;
      //   991: invokevirtual 93	java/lang/StringBuilder:append	(Ljava/lang/String;)Ljava/lang/StringBuilder;
      //   994: pop
      //   995: new 86	java/lang/StringBuilder
      //   998: astore_1
      //   999: aload_1
      //   1000: invokespecial 87	java/lang/StringBuilder:<init>	()V
      //   1003: aload_1
      //   1004: ldc 169
      //   1006: invokevirtual 93	java/lang/StringBuilder:append	(Ljava/lang/String;)Ljava/lang/StringBuilder;
      //   1009: pop
      //   1010: aload_1
      //   1011: aload 19
      //   1013: invokevirtual 93	java/lang/StringBuilder:append	(Ljava/lang/String;)Ljava/lang/StringBuilder;
      //   1016: pop
      //   1017: aload 18
      //   1019: aload_1
      //   1020: invokevirtual 99	java/lang/StringBuilder:toString	()Ljava/lang/String;
      //   1023: invokevirtual 93	java/lang/StringBuilder:append	(Ljava/lang/String;)Ljava/lang/StringBuilder;
      //   1026: pop
      //   1027: aload 18
      //   1029: invokevirtual 99	java/lang/StringBuilder:toString	()Ljava/lang/String;
      //   1032: astore 17
      //   1034: aload_3
      //   1035: astore_1
      //   1036: aload_1
      //   1037: aload 17
      //   1039: invokestatic 174	f6/a:b	(Ljava/lang/String;Ljava/lang/String;)V
      //   1042: new 176	java/net/URL
      //   1045: astore 17
      //   1047: aload 17
      //   1049: aload 18
      //   1051: invokevirtual 99	java/lang/StringBuilder:toString	()Ljava/lang/String;
      //   1054: invokespecial 177	java/net/URL:<init>	(Ljava/lang/String;)V
      //   1057: aload 17
      //   1059: invokevirtual 181	java/net/URL:openConnection	()Ljava/net/URLConnection;
      //   1062: checkcast 183	java/net/HttpURLConnection
      //   1065: astore 17
      //   1067: aload 17
      //   1069: ldc 185
      //   1071: invokevirtual 188	java/net/HttpURLConnection:setRequestMethod	(Ljava/lang/String;)V
      //   1074: aload 17
      //   1076: getstatic 191	e6/a:c	I
      //   1079: invokevirtual 197	java/net/URLConnection:setConnectTimeout	(I)V
      //   1082: aload 17
      //   1084: invokevirtual 200	java/net/URLConnection:connect	()V
      //   1087: new 202	java/lang/String
      //   1090: astore 16
      //   1092: aload 16
      //   1094: aload 17
      //   1096: invokevirtual 206	java/net/URLConnection:getInputStream	()Ljava/io/InputStream;
      //   1099: invokestatic 211	f6/g:b	(Ljava/io/InputStream;)[B
      //   1102: invokespecial 214	java/lang/String:<init>	([B)V
      //   1105: new 86	java/lang/StringBuilder
      //   1108: astore 17
      //   1110: aload 17
      //   1112: invokespecial 87	java/lang/StringBuilder:<init>	()V
      //   1115: aload 17
      //   1117: ldc 216
      //   1119: invokevirtual 93	java/lang/StringBuilder:append	(Ljava/lang/String;)Ljava/lang/StringBuilder;
      //   1122: pop
      //   1123: aload 17
      //   1125: aload 16
      //   1127: invokevirtual 93	java/lang/StringBuilder:append	(Ljava/lang/String;)Ljava/lang/StringBuilder;
      //   1130: pop
      //   1131: aload_1
      //   1132: aload 17
      //   1134: invokevirtual 99	java/lang/StringBuilder:toString	()Ljava/lang/String;
      //   1137: invokestatic 174	f6/a:b	(Ljava/lang/String;Ljava/lang/String;)V
      //   1140: new 218	org/json/JSONObject
      //   1143: astore 17
      //   1145: aload 17
      //   1147: aload 16
      //   1149: invokespecial 219	org/json/JSONObject:<init>	(Ljava/lang/String;)V
      //   1152: aload 17
      //   1154: ldc 221
      //   1156: invokevirtual 224	org/json/JSONObject:optString	(Ljava/lang/String;)Ljava/lang/String;
      //   1159: astore 15
      //   1161: aload 17
      //   1163: ldc 226
      //   1165: iconst_0
      //   1166: invokevirtual 230	org/json/JSONObject:optInt	(Ljava/lang/String;I)I
      //   1169: istore 8
      //   1171: aload 17
      //   1173: aload_2
      //   1174: invokevirtual 224	org/json/JSONObject:optString	(Ljava/lang/String;)Ljava/lang/String;
      //   1177: astore 16
      //   1179: aload_0
      //   1180: astore_1
      //   1181: aload_1
      //   1182: getfield 14	e6/d$a:a	Le6/d;
      //   1185: aload 17
      //   1187: ldc 232
      //   1189: iconst_0
      //   1190: invokevirtual 230	org/json/JSONObject:optInt	(Ljava/lang/String;I)I
      //   1193: invokestatic 235	e6/d:c	(Le6/d;I)I
      //   1196: pop
      //   1197: aload 15
      //   1199: invokestatic 241	android/text/TextUtils:isEmpty	(Ljava/lang/CharSequence;)Z
      //   1202: ifne +75 -> 1277
      //   1205: aload 16
      //   1207: invokestatic 241	android/text/TextUtils:isEmpty	(Ljava/lang/CharSequence;)Z
      //   1210: ifne +67 -> 1277
      //   1213: new 243	e6/e
      //   1216: astore 14
      //   1218: aload 14
      //   1220: aload 16
      //   1222: invokespecial 244	e6/e:<init>	(Ljava/lang/String;)V
      //   1225: invokestatic 246	f6/h:a	()Z
      //   1228: ifne +11 -> 1239
      //   1231: aload 14
      //   1233: getfield 247	e6/e:c	I
      //   1236: ifne +148 -> 1384
      //   1239: aload_1
      //   1240: getfield 14	e6/d$a:a	Le6/d;
      //   1243: aload 17
      //   1245: ldc 249
      //   1247: invokevirtual 224	org/json/JSONObject:optString	(Ljava/lang/String;)Ljava/lang/String;
      //   1250: invokestatic 252	e6/d:e	(Le6/d;Ljava/lang/String;)Ljava/lang/String;
      //   1253: pop
      //   1254: aload_1
      //   1255: getfield 14	e6/d$a:a	Le6/d;
      //   1258: aload 15
      //   1260: invokestatic 254	e6/d:g	(Le6/d;Ljava/lang/String;)Ljava/lang/String;
      //   1263: pop
      //   1264: aload_1
      //   1265: getfield 14	e6/d$a:a	Le6/d;
      //   1268: invokestatic 257	e6/d:h	(Le6/d;)Ljava/lang/Runnable;
      //   1271: invokestatic 262	f6/l:a	(Ljava/lang/Runnable;)V
      //   1274: goto +110 -> 1384
      //   1277: iload 8
      //   1279: bipush 248
      //   1281: if_icmpne +103 -> 1384
      //   1284: aload_1
      //   1285: getfield 14	e6/d$a:a	Le6/d;
      //   1288: aload 17
      //   1290: ldc_w 264
      //   1293: invokevirtual 224	org/json/JSONObject:optString	(Ljava/lang/String;)Ljava/lang/String;
      //   1296: invokestatic 267	e6/d:i	(Le6/d;Ljava/lang/String;)J
      //   1299: lstore 20
      //   1301: lload 20
      //   1303: lstore 6
      //   1305: goto +72 -> 1377
      //   1308: astore 17
      //   1310: goto +50 -> 1360
      //   1313: astore 17
      //   1315: aload_0
      //   1316: astore_1
      //   1317: goto +43 -> 1360
      //   1320: astore 17
      //   1322: goto +5 -> 1327
      //   1325: astore 17
      //   1327: aload_0
      //   1328: astore_1
      //   1329: goto +31 -> 1360
      //   1332: astore 17
      //   1334: aload_0
      //   1335: astore_1
      //   1336: goto +19 -> 1355
      //   1339: astore 17
      //   1341: aload_0
      //   1342: astore_1
      //   1343: goto +12 -> 1355
      //   1346: astore 17
      //   1348: aload_0
      //   1349: astore_1
      //   1350: goto +5 -> 1355
      //   1353: astore 17
      //   1355: goto +5 -> 1360
      //   1358: astore 17
      //   1360: aload_1
      //   1361: getfield 14	e6/d$a:a	Le6/d;
      //   1364: lconst_0
      //   1365: invokestatic 271	e6/d:j	(Le6/d;J)V
      //   1368: aload_3
      //   1369: ldc_w 273
      //   1372: aload 17
      //   1374: invokestatic 276	f6/a:d	(Ljava/lang/String;Ljava/lang/String;Ljava/lang/Throwable;)V
      //   1377: iload 9
      //   1379: istore 8
      //   1381: goto -1345 -> 36
      //   1384: return
      // Local variable table:
      //   start	length	slot	name	signature
      //   0	1385	0	this	a
      //   1	1360	1	localObject1	Object
      //   4	1170	2	str1	String
      //   7	1362	3	str2	String
      //   11	611	4	locale1	e
      //   26	628	5	locale2	e
      //   31	1273	6	l1	long
      //   34	1346	8	i	int
      //   40	1338	9	j	int
      //   51	635	10	str3	String
      //   56	662	11	str4	String
      //   68	688	12	str5	String
      //   73	715	13	str6	String
      //   94	1138	14	localObject2	Object
      //   106	1153	15	str7	String
      //   111	1110	16	str8	String
      //   116	1173	17	localObject3	Object
      //   1308	1	17	localException1	Exception
      //   1313	1	17	localException2	Exception
      //   1320	1	17	localException3	Exception
      //   1325	1	17	localException4	Exception
      //   1332	1	17	localException5	Exception
      //   1339	1	17	localException6	Exception
      //   1346	1	17	localException7	Exception
      //   1353	1	17	localException8	Exception
      //   1358	15	17	localException9	Exception
      //   129	921	18	localStringBuilder	StringBuilder
      //   577	435	19	str9	String
      //   1299	3	20	l2	long
      // Exception table:
      //   from	to	target	type
      //   1181	1239	1308	java/lang/Exception
      //   1239	1274	1308	java/lang/Exception
      //   1284	1301	1308	java/lang/Exception
      //   1171	1179	1313	java/lang/Exception
      //   1161	1171	1320	java/lang/Exception
      //   1036	1161	1325	java/lang/Exception
      //   599	771	1332	java/lang/Exception
      //   771	1034	1332	java/lang/Exception
      //   126	312	1339	java/lang/Exception
      //   312	590	1339	java/lang/Exception
      //   118	126	1346	java/lang/Exception
      //   113	118	1353	java/lang/Exception
      //   48	113	1358	java/lang/Exception
    }
  }
  
  class b
    implements Runnable
  {
    b() {}
    
    /* Error */
    public void run()
    {
      // Byte code:
      //   0: new 23	java/net/URL
      //   3: astore_1
      //   4: aload_1
      //   5: aload_0
      //   6: getfield 14	e6/d$b:a	Le6/d;
      //   9: invokestatic 27	e6/d:f	(Le6/d;)Ljava/lang/String;
      //   12: invokespecial 30	java/net/URL:<init>	(Ljava/lang/String;)V
      //   15: aload_1
      //   16: invokevirtual 34	java/net/URL:openConnection	()Ljava/net/URLConnection;
      //   19: checkcast 36	java/net/HttpURLConnection
      //   22: astore_1
      //   23: aload_1
      //   24: ldc 38
      //   26: invokevirtual 41	java/net/HttpURLConnection:setRequestMethod	(Ljava/lang/String;)V
      //   29: aload_1
      //   30: getstatic 47	e6/a:c	I
      //   33: invokevirtual 53	java/net/URLConnection:setConnectTimeout	(I)V
      //   36: aload_1
      //   37: invokevirtual 56	java/net/URLConnection:connect	()V
      //   40: aload_1
      //   41: invokevirtual 60	java/net/HttpURLConnection:getResponseCode	()I
      //   44: sipush 200
      //   47: if_icmpne +321 -> 368
      //   50: aload_1
      //   51: invokevirtual 64	java/net/URLConnection:getInputStream	()Ljava/io/InputStream;
      //   54: invokestatic 70	f6/g:b	(Ljava/io/InputStream;)[B
      //   57: astore_1
      //   58: aload_0
      //   59: getfield 14	e6/d$b:a	Le6/d;
      //   62: invokestatic 73	e6/d:d	(Le6/d;)Ljava/lang/String;
      //   65: invokestatic 79	android/text/TextUtils:isEmpty	(Ljava/lang/CharSequence;)Z
      //   68: istore_2
      //   69: aconst_null
      //   70: astore_3
      //   71: aconst_null
      //   72: astore 4
      //   74: aconst_null
      //   75: astore 5
      //   77: aload_1
      //   78: astore 6
      //   80: iload_2
      //   81: ifne +30 -> 111
      //   84: aload_1
      //   85: invokestatic 84	f6/n:b	([B)Ljava/lang/String;
      //   88: astore 7
      //   90: aload_1
      //   91: astore 6
      //   93: aload_0
      //   94: getfield 14	e6/d$b:a	Le6/d;
      //   97: invokestatic 73	e6/d:d	(Le6/d;)Ljava/lang/String;
      //   100: aload 7
      //   102: invokevirtual 90	java/lang/String:equalsIgnoreCase	(Ljava/lang/String;)Z
      //   105: ifne +6 -> 111
      //   108: aconst_null
      //   109: astore 6
      //   111: aload 6
      //   113: ifnull +255 -> 368
      //   116: ldc 92
      //   118: invokestatic 97	f6/a:a	(Ljava/lang/String;)Ljava/lang/String;
      //   121: ldc 99
      //   123: invokestatic 104	android/util/Log:d	(Ljava/lang/String;Ljava/lang/String;)I
      //   126: pop
      //   127: new 106	java/io/File
      //   130: astore 8
      //   132: new 108	java/lang/StringBuilder
      //   135: astore_1
      //   136: aload_1
      //   137: invokespecial 109	java/lang/StringBuilder:<init>	()V
      //   140: aload_1
      //   141: aload_0
      //   142: getfield 14	e6/d$b:a	Le6/d;
      //   145: invokestatic 112	e6/d:k	(Le6/d;)Ljava/lang/String;
      //   148: invokevirtual 116	java/lang/StringBuilder:append	(Ljava/lang/String;)Ljava/lang/StringBuilder;
      //   151: pop
      //   152: aload_1
      //   153: ldc 118
      //   155: invokevirtual 116	java/lang/StringBuilder:append	(Ljava/lang/String;)Ljava/lang/StringBuilder;
      //   158: pop
      //   159: aload 8
      //   161: aload_1
      //   162: invokevirtual 122	java/lang/StringBuilder:toString	()Ljava/lang/String;
      //   165: invokespecial 123	java/io/File:<init>	(Ljava/lang/String;)V
      //   168: aload_3
      //   169: astore 7
      //   171: new 125	java/io/FileOutputStream
      //   174: astore_1
      //   175: aload_3
      //   176: astore 7
      //   178: aload_1
      //   179: aload 8
      //   181: invokespecial 128	java/io/FileOutputStream:<init>	(Ljava/io/File;)V
      //   184: aload_1
      //   185: aload 6
      //   187: invokevirtual 132	java/io/FileOutputStream:write	([B)V
      //   190: aload_1
      //   191: invokevirtual 137	java/io/OutputStream:flush	()V
      //   194: aload_1
      //   195: invokevirtual 140	java/io/FileOutputStream:close	()V
      //   198: aload_3
      //   199: astore 7
      //   201: aload_0
      //   202: getfield 14	e6/d$b:a	Le6/d;
      //   205: invokestatic 143	e6/d:a	(Le6/d;)Landroid/content/Context;
      //   208: aload 8
      //   210: invokestatic 148	f6/b:b	(Landroid/content/Context;Ljava/io/File;)[Landroid/content/pm/Signature;
      //   213: invokestatic 153	f6/e:b	([Landroid/content/pm/Signature;)Z
      //   216: ifeq +64 -> 280
      //   219: aload_3
      //   220: astore 7
      //   222: ldc 92
      //   224: invokestatic 97	f6/a:a	(Ljava/lang/String;)Ljava/lang/String;
      //   227: ldc 155
      //   229: invokestatic 104	android/util/Log:d	(Ljava/lang/String;Ljava/lang/String;)I
      //   232: pop
      //   233: aload_3
      //   234: astore 7
      //   236: new 106	java/io/File
      //   239: astore_1
      //   240: aload_3
      //   241: astore 7
      //   243: aload_1
      //   244: aload_0
      //   245: getfield 14	e6/d$b:a	Le6/d;
      //   248: invokestatic 112	e6/d:k	(Le6/d;)Ljava/lang/String;
      //   251: invokespecial 123	java/io/File:<init>	(Ljava/lang/String;)V
      //   254: aload_3
      //   255: astore 7
      //   257: aload 8
      //   259: aload_1
      //   260: invokevirtual 159	java/io/File:renameTo	(Ljava/io/File;)Z
      //   263: pop
      //   264: aload_3
      //   265: astore 7
      //   267: aload_0
      //   268: getfield 14	e6/d$b:a	Le6/d;
      //   271: invokestatic 162	e6/d:l	(Le6/d;)V
      //   274: aload 5
      //   276: astore_1
      //   277: goto +20 -> 297
      //   280: aload_3
      //   281: astore 7
      //   283: ldc 92
      //   285: invokestatic 97	f6/a:a	(Ljava/lang/String;)Ljava/lang/String;
      //   288: ldc 164
      //   290: invokestatic 167	android/util/Log:e	(Ljava/lang/String;Ljava/lang/String;)I
      //   293: pop
      //   294: aload 5
      //   296: astore_1
      //   297: aload_1
      //   298: invokestatic 170	f6/g:a	(Ljava/io/Closeable;)V
      //   301: goto +67 -> 368
      //   304: astore 6
      //   306: aload_1
      //   307: astore 7
      //   309: aload 6
      //   311: astore_1
      //   312: goto +36 -> 348
      //   315: astore 6
      //   317: goto +12 -> 329
      //   320: astore_1
      //   321: goto +27 -> 348
      //   324: astore 6
      //   326: aload 4
      //   328: astore_1
      //   329: aload_1
      //   330: astore 7
      //   332: ldc 92
      //   334: invokestatic 97	f6/a:a	(Ljava/lang/String;)Ljava/lang/String;
      //   337: ldc 172
      //   339: aload 6
      //   341: invokestatic 175	android/util/Log:e	(Ljava/lang/String;Ljava/lang/String;Ljava/lang/Throwable;)I
      //   344: pop
      //   345: goto -48 -> 297
      //   348: aload 7
      //   350: invokestatic 170	f6/g:a	(Ljava/io/Closeable;)V
      //   353: aload_1
      //   354: athrow
      //   355: astore_1
      //   356: ldc 92
      //   358: invokestatic 97	f6/a:a	(Ljava/lang/String;)Ljava/lang/String;
      //   361: ldc 177
      //   363: aload_1
      //   364: invokestatic 180	android/util/Log:w	(Ljava/lang/String;Ljava/lang/String;Ljava/lang/Throwable;)I
      //   367: pop
      //   368: return
      // Local variable table:
      //   start	length	slot	name	signature
      //   0	369	0	this	b
      //   3	309	1	localObject1	Object
      //   320	1	1	localObject2	Object
      //   328	26	1	localObject3	Object
      //   355	9	1	localException1	Exception
      //   68	13	2	bool	boolean
      //   70	211	3	localObject4	Object
      //   72	255	4	localObject5	Object
      //   75	220	5	localObject6	Object
      //   78	108	6	localObject7	Object
      //   304	6	6	localObject8	Object
      //   315	1	6	localException2	Exception
      //   324	16	6	localException3	Exception
      //   88	261	7	localObject9	Object
      //   130	128	8	localFile	java.io.File
      // Exception table:
      //   from	to	target	type
      //   184	198	304	finally
      //   184	198	315	java/lang/Exception
      //   171	175	320	finally
      //   178	184	320	finally
      //   201	219	320	finally
      //   222	233	320	finally
      //   236	240	320	finally
      //   243	254	320	finally
      //   257	264	320	finally
      //   267	274	320	finally
      //   283	294	320	finally
      //   332	345	320	finally
      //   171	175	324	java/lang/Exception
      //   178	184	324	java/lang/Exception
      //   201	219	324	java/lang/Exception
      //   222	233	324	java/lang/Exception
      //   236	240	324	java/lang/Exception
      //   243	254	324	java/lang/Exception
      //   257	264	324	java/lang/Exception
      //   267	274	324	java/lang/Exception
      //   283	294	324	java/lang/Exception
      //   0	69	355	java/lang/Exception
      //   84	90	355	java/lang/Exception
      //   93	108	355	java/lang/Exception
      //   116	168	355	java/lang/Exception
      //   297	301	355	java/lang/Exception
      //   348	355	355	java/lang/Exception
    }
  }
  
  static abstract interface c
  {
    public abstract void a(String paramString, boolean paramBoolean);
  }
}


/* Location:           J:\AndroidKiller_v1.3.1\AndroidKiller_v1.3.1\projects\小米日历-v13.18.0.0\ProjectSrc\smali\
 * Qualified Name:     e6.d
 * JD-Core Version:    0.7.0.1
 */