package androidx.work;

import com.google.common.util.concurrent.ListenableFuture;
import kotlin.Metadata;
import kotlinx.coroutines.n;

@Metadata(bv={}, d1={""}, d2={"R", "Lkotlin/u;", "<anonymous>"}, k=3, mv={1, 5, 1})
public final class j
  implements Runnable
{
  public j(n<Object> paramn, ListenableFuture<Object> paramListenableFuture) {}
  
  /* Error */
  public final void run()
  {
    // Byte code:
    //   0: aload_0
    //   1: getfield 29	androidx/work/j:a	Lkotlinx/coroutines/n;
    //   4: aload_0
    //   5: getfield 31	androidx/work/j:b	Lcom/google/common/util/concurrent/ListenableFuture;
    //   8: invokeinterface 44 1 0
    //   13: invokestatic 50	kotlin/Result:constructor-impl	(Ljava/lang/Object;)Ljava/lang/Object;
    //   16: invokeinterface 56 2 0
    //   21: goto +60 -> 81
    //   24: astore_1
    //   25: aload_1
    //   26: invokevirtual 62	java/lang/Throwable:getCause	()Ljava/lang/Throwable;
    //   29: astore_2
    //   30: aload_2
    //   31: astore_3
    //   32: aload_2
    //   33: ifnonnull +5 -> 38
    //   36: aload_1
    //   37: astore_3
    //   38: aload_1
    //   39: instanceof 64
    //   42: ifeq +17 -> 59
    //   45: aload_0
    //   46: getfield 29	androidx/work/j:a	Lkotlinx/coroutines/n;
    //   49: aload_3
    //   50: invokeinterface 70 2 0
    //   55: pop
    //   56: goto +25 -> 81
    //   59: aload_0
    //   60: getfield 29	androidx/work/j:a	Lkotlinx/coroutines/n;
    //   63: astore_2
    //   64: getstatic 74	kotlin/Result:Companion	Lkotlin/Result$a;
    //   67: astore_1
    //   68: aload_2
    //   69: aload_3
    //   70: invokestatic 79	kotlin/j:a	(Ljava/lang/Throwable;)Ljava/lang/Object;
    //   73: invokestatic 50	kotlin/Result:constructor-impl	(Ljava/lang/Object;)Ljava/lang/Object;
    //   76: invokeinterface 56 2 0
    //   81: return
    // Local variable table:
    //   start	length	slot	name	signature
    //   0	82	0	this	j
    //   24	15	1	localObject1	Object
    //   67	1	1	locala	kotlin.Result.a
    //   29	40	2	localObject2	Object
    //   31	39	3	localObject3	Object
    // Exception table:
    //   from	to	target	type
    //   0	21	24	finally
  }
}


/* Location:           J:\AndroidKiller_v1.3.1\AndroidKiller_v1.3.1\projects\小米日历-v13.18.0.0\ProjectSrc\smali\
 * Qualified Name:     androidx.work.j
 * JD-Core Version:    0.7.0.1
 */